{"is_source_file": true, "format": "Dart", "description": "This Dart source file defines a Flutter widget 'ClientsPage' for managing clients, including CRUD operations, pagination, and displaying a list of clients. It includes internal classes for dialog forms and pagination controls, utilizing provider for state management.", "external_files": ["../../state/feature_providers.dart", "../../models/core_models.dart"], "external_methods": ["context.read<ClientsProvider>()", "context.watch<ClientsProvider>()", "Theme.of(context).colorScheme", "showDialog", "Navigator.pop", "Navigator.of(context).pop", "MaterialApp themes and widgets", "Provider package methods"], "published": ["ClientsPage"], "classes": [{"name": "ClientsPage", "description": "A stateful widget representing the clients management page with CRUD operations, pagination, and list display."}, {"name": "_ClientsPageState", "description": "State class for ClientsPage handling initial load, UI building, and interactions like delete and form opening."}, {"name": "_PaginationBar", "description": "A widget displaying pagination controls with 'Page' label, previous and next buttons."}, {"name": "_ClientFormDialog", "description": "A stateful widget presenting a form dialog for creating or editing a client."}, {"name": "_ClientFormDialogState", "description": "State class managing the form's input controllers, validation, and submit logic for the client form."}], "methods": [{"name": "didChangeDependencies", "description": "Overrides to perform initial load of client data once dependencies change."}, {"name": "build", "description": "Builds the UI for the ClientsPage, including list, pagination, and actions."}, {"name": "_confirmDelete", "description": "Shows a confirmation dialog and deletes a client if confirmed."}, {"name": "_openForm", "description": "Opens the client creation/edit dialog."}, {"name": "initState", "description": "Initializes form controllers and sets existing client data for editing."}, {"name": "dispose", "description": "Disposes of form controllers."}, {"name": "build", "description": "Builds the form dialog UI for creating/updating a client."}, {"name": "onPressed", "description": "Handlers for buttons like Save, Cancel, navigating pages, and editing/deleting clients."}], "calls": ["context.read<ClientsProvider>()", "context.watch<ClientsProvider>()", "Theme.of(context).textTheme.titleLarge", "showDialog", "Navigator.pop", "Navigator.of(context).pop", "provider.load", "provider.remove", "provider.submitCreate", "provider.submitUpdate"], "search-terms": ["clients management", "pagination control", "client form dialog", "CRUD operations", "Flutter state management", "Provider package", "ClientModel", "fitmanage"], "state": 2, "file_id": 26, "knowledge_revision": 127, "git_revision": "", "revision_history": [{"55": ""}, {"92": ""}, {"113": ""}, {"119": ""}, {"123": ""}, {"127": ""}], "hash": "5ffd131982f629b1a0862480e2717e1a", "format-version": 4, "code-base-name": "fitness_nutrition_frontend", "filename": "fitness_nutrition_frontend/lib/ui/pages/clients_page.dart"}